{"cameraMode":{"drawMode":0,"name":"Shaded","section":"Shading Mode"},"sceneLighting":true,"audioPlay":false,"sceneViewState":{"m_AlwaysRefresh":false,"showFog":true,"showSkybox":true,"showFlares":true,"showImageEffects":true,"showParticleSystems":true,"showVisualEffectGraphs":true,"m_FxEnabled":true},"in2DMode":false,"pivot":{"x":-2.7140612602233888,"y":-4.369521141052246,"z":0.3484678566455841},"rotation":{"x":0.3776848614215851,"y":0.00693990383297205,"z":-0.0028342183213680984,"w":0.9258973002433777},"size":10.0,"orthographic":false}